timeskorch/__init__.py
timeskorch-0.0.1.dist-info/METADATA
timeskorch-0.0.1.dist-info/WHEEL
timeskorch-0.0.1.dist-info/top_level.txt
timeskorch-0.0.1.dist-info/RECORD
