Metadata-Version: 2.1
Name: timeskorch
Version: 0.0.1
Summary: Time Skorch (TS) is a powerful tool designed to make time series analysis and forecasting a breeze.
Home-page: https://github.com/minqukanq/timeskorch
Author: mingukang
Author-email: kang.mingu94@gmail.com
Keywords: time series,sklearn,pytorch,skorch,deep learning
Classifier: Programming Language :: Python :: 3
Classifier: License :: OSI Approved :: Apache Software License
Classifier: Operating System :: OS Independent
Requires-Python: >=3.6
Requires-Dist: scikit-learn
Requires-Dist: skorch
